office_cracker/__init__.py
office_cracker/office_cracker.py
office_cracker-0.1.0.dist-info/METADATA
office_cracker-0.1.0.dist-info/WHEEL
office_cracker-0.1.0.dist-info/top_level.txt
office_cracker-0.1.0.dist-info/RECORD
