Metadata-Version: 2.1
Name: office-cracker
Version: 0.1.0
Summary: advance office 365 cracker 
Home-page: https://t.me/UnkownxArmy
Author: agent 047
Author-email: khalidziraoui6@gmail.com@example.com
Classifier: Programming Language :: Python :: 2.6
Classifier: License :: OSI Approved :: MIT License
Classifier: Operating System :: OS Independent
Requires-Python: >=2.6
